pylab/__init__.py
pylab/pylab.py
scibag/__init__.py
scibag/scibag.py
scibag-0.2.1.dist-info/DESCRIPTION.rst
scibag-0.2.1.dist-info/METADATA
scibag-0.2.1.dist-info/metadata.json
scibag-0.2.1.dist-info/RECORD
scibag-0.2.1.dist-info/top_level.txt
scibag-0.2.1.dist-info/WHEEL
