Metadata-Version: 2.0
Name: scibag
Version: 0.2.1
Summary: Data science meta-package
Home-page: https://github.com/javipalanca/scibag
Author: Javi Palanca
Author-email: jpalanca@gmail.com
License: BSD
Keywords: scibag
Platform: UNKNOWN
Classifier: Development Status :: 7 - Inactive
Classifier: Intended Audience :: Developers
Classifier: License :: OSI Approved :: BSD License
Classifier: Natural Language :: English
Classifier: Programming Language :: Python :: 2
Classifier: Programming Language :: Python :: 2.6
Classifier: Programming Language :: Python :: 2.7
Classifier: Programming Language :: Python :: 3
Classifier: Programming Language :: Python :: 3.3
Classifier: Programming Language :: Python :: 3.4
Obsoletes: p
Obsoletes: y
Obsoletes: l
Obsoletes: a
Obsoletes: b
Requires-Dist: scikit-learn
Requires-Dist: scikit-image
Requires-Dist: networkx
Requires-Dist: jsonschema
Requires-Dist: tornado
Requires-Dist: ipython
Requires-Dist: jinja2
Requires-Dist: pytz
Requires-Dist: pyzmq
Requires-Dist: sympy
Requires-Dist: scipy
Requires-Dist: pandas
Requires-Dist: seaborn
Requires-Dist: matplotlib
Requires-Dist: numpy
